.gitignore
LICENSE
PKG-INFO
README.md
__init__.py
gophers.py
pyproject.toml
requirements.txt
go_module/go.mod
go_module/go.sum
go_module/gophers_py.go
go_module/Darwin/gophers_py.h
go_module/Darwin/gophers_py.so
go_module/Windows/gophers_py.h
go_module/Windows/gophers_py.so
gophers/LICENSE
gophers/README.md
gophers/__init__.py
gophers/gophers.py
gophers/pyproject.toml
gophers/requirements.txt
gophers/go_module/go.mod
gophers/go_module/go.sum
gophers/go_module/gophers_py.go
gophers/go_module/Darwin/gophers_py.h
gophers/go_module/Darwin/gophers_py.so
gophers/go_module/Windows/gophers_py.h
gophers/go_module/Windows/gophers_py.so
gophers-0.4.5.dist-info/METADATA
gophers-0.4.5.dist-info/WHEEL
gophers-0.4.5.dist-info/licenses/LICENSE
gophers-0.4.5.dist-info/RECORD
